Metadata-Version: 1.0
Name: ckippy
Version: 0.0.1
Summary: A Python2/3 API for CKIP Chinese Parser demo version.You can use the CKIP Chinese Parse without registration or login.
Home-page: UNKNOWN
Author: Aji (阿吉)
Author-email: amigcamel@gmail.com
License: UNKNOWN
Platform: UNKNOWN
